{
  "description": "A customizable select component used to pick a value from a list of options",
  "properties": [
    {
      "name": "bordered",
      "type": "boolean",
      "description": "Indicates that the input should have a border.",
      "default": "true",
      "mutable": false,
      "end_line": 39
    },
    {
      "name": "customClass",
      "type": "string",
      "description": "Custom CSS class to apply to the inner div.",
      "default": "''",
      "mutable": false,
      "end_line": 42
    },
    {
      "name": "disabled",
      "type": "boolean",
      "description": "Whether the form control is disabled.",
      "default": "false",
      "mutable": false,
      "end_line": 45
    },
    {
      "name": "feedback",
      "type": "IInputFeedbackProp",
      "description": "Feedback to render below the input.",
      "default": null,
      "mutable": false,
      "end_line": 48
    },
    {
      "name": "inputId",
      "type": "string",
      "description": "The ID of the input element.",
      "default": null,
      "mutable": false,
      "end_line": 51
    },
    {
      "name": "inputTabIndex",
      "type": "number",
      "description": "Determine the control's relative ordering for sequential focus navigation (typically with the Tab key).",
      "default": null,
      "mutable": false,
      "end_line": 54
    },
    {
      "name": "label",
      "type": "string",
      "description": "The text to display within the label.",
      "default": null,
      "mutable": false,
      "end_line": 57
    },
    {
      "name": "name",
      "type": "string",
      "description": "Name of the form control. Submitted with the form as part of a name/value pair.",
      "default": null,
      "mutable": false,
      "end_line": 60
    },
    {
      "name": "options",
      "type": "ISelectOption[]",
      "description": "The options to display in the select dropdown.",
      "default": "[]",
      "mutable": true,
      "end_line": 63
    },
    {
      "name": "required",
      "type": "boolean",
      "description": "A value is required for the form to be submittable.",
      "default": "false",
      "mutable": false,
      "end_line": 66
    },
    {
      "name": "size",
      "type": "ModusSize",
      "description": "The size of the input.",
      "default": "'md'",
      "mutable": false,
      "end_line": 69
    },
    {
      "name": "value",
      "type": "string",
      "description": "The value of the control.",
      "default": "''",
      "mutable": true,
      "end_line": 72
    }
  ],
  "events": [
    {
      "name": "inputBlur",
      "detail": "FocusEvent",
      "description": "Event emitted when the input loses focus.",
      "end_line": 75
    },
    {
      "name": "inputChange",
      "detail": "InputEvent",
      "description": "Event emitted when the input value changes.",
      "end_line": 78
    },
    {
      "name": "inputFocus",
      "detail": "FocusEvent",
      "description": "Event emitted when the input gains focus.",
      "end_line": 81
    }
  ],
  "methods": [],
  "slots": [],
  "examples": {
    "basic": "<select-shadow-host\n      .props=${{ ...args }}\n    ></select-shadow-host>",
    "variations": [],
    "args": {
      "bordered": "true",
      "disabled": "false",
      "label": "'Label'",
      "size": "'md'",
      "value": "''"
    },
    "argTypes": {},
    "usage": [],
    "events": [
      "inputBlur",
      "inputChange",
      "inputFocus"
    ]
  },
  "scripts": [
    {
      "title": "Basic Usage",
      "code": "<modus-wc-select feedback=\"example-feedback\" inputId=\"example-inputId\" inputTabIndex=\"example-inputTabIndex\" label=\"example-label\" name=\"example-name\"></modus-wc-select>",
      "description": "Minimal required properties"
    },
    {
      "title": "Event Handling",
      "code": "<modus-wc-select onInputBlur={(e) => handleInputBlur(e.detail)} onInputChange={(e) => handleInputChange(e.detail)} onInputFocus={(e) => handleInputFocus(e.detail)}></modus-wc-select>",
      "description": "Handling component events"
    }
  ],
  "tag": "modus-wc-select",
  "storyExample": {
    "template": "<select-shadow-host\n      .props=${{ ...args }}\n    ></select-shadow-host>",
    "args": {
      "bordered": "true",
      "disabled": "false",
      "label": "'Label'",
      "size": "'md'",
      "value": "''"
    },
    "argTypes": {},
    "events": [
      "inputBlur",
      "inputChange",
      "inputFocus"
    ],
    "fullContent": "import { withActions } from '@storybook/addon-actions/decorator';\nimport { Meta, StoryObj } from '@storybook/web-components';\nimport { html } from 'lit';\nimport { ifDefined } from 'lit/directives/if-defined.js';\nimport { ISelectOption } from './modus-wc-select';\nimport { createShadowHostClass } from '../../providers/shadow-dom/shadow-host-helper';\nimport { IInputFeedbackProp, ModusSize } from '../types';\n\nconst options: ISelectOption[] = [\n  { label: 'Option 1', value: '1' },\n  { label: 'Option 2', value: '2' },\n  { label: 'Option 3', value: '3' },\n];\n\ninterface SelectArgs {\n  bordered?: boolean;\n  'custom-class'?: string;\n  disabled?: boolean;\n  feedback?: IInputFeedbackProp;\n  'input-aria-invalid'?: 'true' | 'false';\n  'input-id'?: string;\n  'input-tab-index'?: number;\n  label?: string;\n  name?: string;\n  options: ISelectOption[];\n  required?: boolean;\n  size?: ModusSize;\n  value: string;\n}\n\nconst meta: Meta<SelectArgs> = {\n  title: 'Components/Forms/Select',\n  component: 'modus-wc-select',\n  args: {\n    bordered: true,\n    disabled: false,\n    label: 'Label',\n    options,\n    size: 'md',\n    value: '',\n  },\n  argTypes: {\n    feedback: {\n      description: 'Feedback prop for input components',\n      table: {\n        type: {\n          detail: `\n            Interface: IInputFeedbackProp\n            Properties:\n            - level ('error' | 'info' | 'success' | 'warning'): The feedback level\n            - message (string, optional): The feedback message\n          `,\n        },\n      },\n    },\n    'input-aria-invalid': {\n      control: { type: 'select' },\n      options: ['true', 'false'],\n    },\n    options: {\n      description: 'Array of option objects for the select dropdown',\n      table: {\n        type: {\n          detail: `\n            Interface: ISelectOption\n            Properties:\n            - disabled (boolean, optional): Whether the option is disabled and cannot be selected\n            - label (string): Display text for the option\n            - value (string): The value of the option\n          `,\n        },\n      },\n    },\n    size: {\n      control: { type: 'select' },\n      options: ['sm', 'md', 'lg'],\n    },\n  },\n  decorators: [withActions],\n  parameters: {\n    actions: {\n      handles: ['inputBlur', 'inputChange', 'inputFocus'],\n    },\n  },\n};\n\nexport default meta;\n\ntype Story = StoryObj<SelectArgs>;\n\nexport const Default: Story = {\n  render: (args) => html`\n    <modus-wc-select\n      aria-label=\"Select input\"\n      ?bordered=${args.bordered}\n      custom-class=${ifDefined(args['custom-class'])}\n      ?disabled=${args.disabled}\n      .feedback=${args.feedback}\n      input-aria-invalid=${ifDefined(args['input-aria-invalid'])}\n      input-id=${ifDefined(args['input-id'])}\n      input-tab-index=${ifDefined(args['input-tab-index'])}\n      label=${ifDefined(args.label)}\n      name=${ifDefined(args.name)}\n      .options=${args.options}\n      ?required=${args.required}\n      size=${ifDefined(args.size)}\n      .value=${args.value}\n    ></modus-wc-select>\n    <script>\n      const options = [\n        { label: 'Option 1', value: '1' },\n        { label: 'Option 2', value: '2' },\n        { label: 'Option 3', value: '3' },\n      ];\n      // Adding this block to show how to set options via JS\n      // const select = document.querySelector('modus-wc-select');\n      // select.options = options;\n    </script>\n  `,\n};\n\nconst errorFeedback: IInputFeedbackProp = {\n  level: 'error',\n  message: 'Value is required.',\n};\n\nexport const WithErrorFeedback: Story = {\n  render: (args) => html`\n    <modus-wc-select\n      aria-label=\"Select input\"\n      .feedback=${errorFeedback}\n      id=\"error-select\"\n      label=${ifDefined(args.label)}\n      .options=${[]}\n      ?required=${true}\n      .value=${args.value}\n    ></modus-wc-select>\n    <script>\n      // Adding this block to show how to set feedback via JS\n      // const select = document.getElementById('error-select');\n      // select.feedback = { level: 'error', message: 'Value is required.' };\n    </script>\n  `,\n};\n\nexport const ShadowDomParent: Story = {\n  render: (args) => {\n    // Create a unique shadow host for select component\n    if (!customElements.get('select-shadow-host')) {\n      const SelectShadowHost = createShadowHostClass<SelectArgs>({\n        componentTag: 'modus-wc-select',\n        propsMapper: (v: SelectArgs, el: HTMLElement) => {\n          const selectEl = el as unknown as {\n            bordered: boolean;\n            customClass: string;\n            disabled: boolean;\n            feedback: IInputFeedbackProp;\n            inputId: string;\n            inputTabIndex: number;\n            label: string;\n            name: string;\n            options: ISelectOption[];\n            required: boolean;\n            size: string;\n            value: string;\n          };\n          selectEl.bordered = Boolean(v.bordered);\n          selectEl.customClass = v['custom-class'] || '';\n          selectEl.disabled = Boolean(v.disabled);\n          selectEl.inputId = v['input-id'] || '';\n          selectEl.inputTabIndex = v['input-tab-index'] || 0;\n          selectEl.label = v.label || '';\n          selectEl.name = v.name || '';\n          selectEl.options = v.options;\n          selectEl.required = Boolean(v.required);\n          selectEl.size = v.size || 'md';\n          selectEl.value = v.value;\n        },\n      });\n      customElements.define('select-shadow-host', SelectShadowHost);\n    }\n\n    return html`<select-shadow-host\n      .props=${{ ...args }}\n    ></select-shadow-host>`;\n  },\n};\n\nexport const Migration: Story = {\n  parameters: {\n    docs: {\n      description: {\n        story: `\n#### Breaking Changes\n\n  - In 1.0 input state was maintained by the component. 2.0 components encourage users to follow a controlled\n  input model. See the Form Inputs [documentation](/docs/documentation-form-inputs--docs) for\n  additional info and examples.\n  - The options format has changed to use a standardized \\`ISelectOption\\` object array.\n  - Size values have changed from verbose names (\\`medium\\`, \\`large\\`) to abbreviations (\\`sm\\`, \\`md\\`, \\`lg\\`).\n\n#### Prop Mapping\n\n| 1.0 Prop              | 2.0 Prop            | Notes                                                |\n|-----------------------|---------------------|------------------------------------------------------|\n| aria-label            | aria-label          |                                                      |\n| disabled              | disabled            |                                                      |\n| error-text            | feedback.message    | Use \\`feedback\\` level                               |\n| helper-text           |                     | Not carried over                                     |\n| label                 | label               |                                                      |\n| options               | options             | Format changed to require array of \\`ISelectOption\\` objects |\n| options-display-prop  |                     | Not carried over                                     |\n| placeholder           |                     | Not carried over                                     |\n| required              | required            |                                                      |\n| size                  | size                | \\`medium\\` \u2192 \\`md\\`, \\`large\\` \u2192 \\`lg\\`              |\n| valid-text            | feedback.message    | Use \\`feedback\\` level                               |\n| value                 | value               |                                                      |\n\n#### Event Mapping\n\n| 1.0 Event    | 2.0 Event   | Notes            |\n|--------------|-------------|------------------|\n| valueChange  | inputChange |                  |\n| inputBlur    | inputBlur   |                  |\n        `,\n      },\n    },\n    controls: { disable: true },\n    canvas: { disable: true },\n  },\n  render: () => html`<div></div>`,\n};\n"
  }
}